{
  "_class": "group",
  "booleanOperation": -1,
  "clippingMaskMode": 0,
  "do_objectID": "D686E50A-1493-4506-891F-0B82534BC18F",
  "exportOptions": {
    "_class": "exportOptions",
    "do_objectID": "838F9F75-AEE0-4A64-BB10-B151685642D4",
    "exportFormats": [
    ],
    "includedLayerIds": [
    ],
    "layerOptions": 0,
    "shouldTrim": false
  },
  "frame": {
    "_class": "rect",
    "constrainProportions": false,
    "do_objectID": "C7395638-8764-4040-9459-1C7C30627BDC",
    "height": 8.691292875989445,
    "width": 8.691292875989445,
    "x": 20.27968337730871,
    "y": 1.448548812664908
  },
  "hasClickThrough": false,
  "hasClippingMask": false,
  "isFixedToViewport": false,
  "isFlippedHorizontal": false,
  "isFlippedVertical": false,
  "isLocked": false,
  "isVisible": true,
  "layerListExpandedType": 0,
  "layers": [
    {
      "class": "shapePath",
      "id": "CEFDB5D8-1DAC-48A4-92FE-73A5D35B8601"
    },
    {
      "class": "shapeGroup",
      "id": "77C10056-3074-4EE3-9E2E-0496A6E862D8"
    }
  ],
  "name": "Group 3",
  "nameIsFixed": false,
  "resizingConstraint": 63,
  "resizingType": 0,
  "rotation": 0,
  "shouldBreakMaskChain": false,
  "style": {
    "_class": "style",
    "blur": {
      "_class": "blur",
      "center": "{0.5, 0.5}",
      "do_objectID": "423667B5-782E-40C9-90D4-4DEB90355FDC",
      "isEnabled": false,
      "motionAngle": 0,
      "radius": 4.828496042216359,
      "saturation": 1,
      "type": 0
    },
    "do_objectID": "7CCB059C-BAE5-4657-9679-F83CB34078C4",
    "endMarkerType": 0,
    "miterLimit": 10,
    "startMarkerType": 0,
    "windingRule": 1
  }
}