{
  "_class": "text",
  "attributedString": {
    "_class": "attributedString",
    "attributes": [
      {
        "_class": "stringAttribute",
        "attributes": {
          "MSAttributedStringColorAttribute": {
            "_class": "color",
            "alpha": 1,
            "blue": 0,
            "green": 0,
            "red": 0
          },
          "MSAttributedStringFontAttribute": {
            "_class": "fontDescriptor",
            "attributes": {
              "name": "Perpetua-Bold",
              "size": 32
            }
          },
          "paragraphStyle": {
            "_class": "paragraphStyle",
            "alignment": 2
          },
          "textStyleVerticalAlignmentKey": 0
        },
        "length": 1,
        "location": 0
      }
    ],
    "string": "2"
  },
  "automaticallyDrawOnUnderlyingPath": false,
  "booleanOperation": -1,
  "clippingMaskMode": 0,
  "do_objectID": "9D1D5BD3-E767-453A-9958-E9FC6639E9F8",
  "dontSynchroniseWithSymbol": false,
  "exportOptions": {
    "_class": "exportOptions",
    "do_objectID": "DA1DB7EA-265A-4AC9-AD4C-C23E921C55ED",
    "exportFormats": [
    ],
    "includedLayerIds": [
    ],
    "layerOptions": 0,
    "shouldTrim": false
  },
  "frame": {
    "_class": "rect",
    "constrainProportions": false,
    "do_objectID": "B6089A67-D4A4-4FCE-810E-778F9BD5561D",
    "height": 36,
    "width": 27,
    "x": 426,
    "y": 1781
  },
  "glyphBounds": "{{7, 6}, {13, 20}}",
  "hasClippingMask": false,
  "isFixedToViewport": false,
  "isFlippedHorizontal": false,
  "isFlippedVertical": false,
  "isLocked": false,
  "isVisible": true,
  "layerListExpandedType": 0,
  "lineSpacingBehaviour": 2,
  "name": "2",
  "nameIsFixed": false,
  "resizingConstraint": 63,
  "resizingType": 0,
  "rotation": 0,
  "sharedStyleID": "40B7DEF7-FF91-4BF6-A190-F5C733E1F20E",
  "shouldBreakMaskChain": false,
  "style": {
    "_class": "style",
    "do_objectID": "7C6F616D-52F6-4F1B-ABB7-0A87CAFE1062",
    "endMarkerType": 0,
    "miterLimit": 10,
    "startMarkerType": 0,
    "textStyle": {
      "_class": "textStyle",
      "do_objectID": "4B3FE4EC-89E9-4542-B588-E9EF641368FD",
      "encodedAttributes": {
        "MSAttributedStringColorAttribute": {
          "_class": "color",
          "alpha": 1,
          "blue": 0,
          "green": 0,
          "red": 0
        },
        "MSAttributedStringFontAttribute": {
          "_class": "fontDescriptor",
          "attributes": {
            "name": "Perpetua-Bold",
            "size": 32
          }
        },
        "paragraphStyle": {
          "_class": "paragraphStyle",
          "alignment": 2
        },
        "textStyleVerticalAlignmentKey": 0
      },
      "verticalAlignment": 0
    },
    "windingRule": 1
  },
  "textBehaviour": 1
}