{
  "_class": "group",
  "booleanOperation": -1,
  "clippingMaskMode": 0,
  "do_objectID": "F975D522-9E92-4F01-AF87-D20A6D341F93",
  "exportOptions": {
    "_class": "exportOptions",
    "do_objectID": "3F134924-1B25-494B-BD4F-1E1C9A64A4BB",
    "exportFormats": [
    ],
    "includedLayerIds": [
    ],
    "layerOptions": 0,
    "shouldTrim": false
  },
  "frame": {
    "_class": "rect",
    "constrainProportions": false,
    "do_objectID": "49153C69-ED5B-4E0B-ABB4-110DF9B683D7",
    "height": 70,
    "width": 306,
    "x": 35,
    "y": 6256
  },
  "hasClickThrough": false,
  "hasClippingMask": false,
  "isFixedToViewport": false,
  "isFlippedHorizontal": false,
  "isFlippedVertical": false,
  "isLocked": false,
  "isVisible": true,
  "layerListExpandedType": 0,
  "layers": [
    {
      "class": "rectangle",
      "id": "C40A7274-C309-4BF0-9509-8A1C32AEE9B5"
    },
    {
      "class": "text",
      "id": "DF862879-0DC0-449A-A5F6-B26D7EA92105"
    }
  ],
  "name": "project text detail copy 31",
  "nameIsFixed": true,
  "resizingConstraint": 63,
  "resizingType": 0,
  "rotation": 0,
  "shouldBreakMaskChain": false,
  "style": {
    "_class": "style",
    "do_objectID": "42C488F1-7970-483C-B59F-B736F550C275",
    "endMarkerType": 0,
    "miterLimit": 10,
    "startMarkerType": 0,
    "windingRule": 1
  }
}