{
  "_class": "shapePath",
  "booleanOperation": -1,
  "clippingMaskMode": 0,
  "do_objectID": "9C4C9132-337D-42F0-B9AA-55D64E851B23",
  "edited": true,
  "exportOptions": {
    "_class": "exportOptions",
    "do_objectID": "27AD8A70-5E88-4D5E-ABD0-AF19AF4BB276",
    "exportFormats": [
    ],
    "includedLayerIds": [
    ],
    "layerOptions": 0,
    "shouldTrim": false
  },
  "frame": {
    "_class": "rect",
    "constrainProportions": false,
    "do_objectID": "52E0842E-C117-41B0-89FC-EFB2590E41B3",
    "height": 44.49136651583717,
    "width": 44.69405266217661,
    "x": 0.2880762509748612,
    "y": 0.4068277526395023
  },
  "hasClippingMask": false,
  "isClosed": true,
  "isFixedToViewport": false,
  "isFlippedHorizontal": false,
  "isFlippedVertical": false,
  "isLocked": false,
  "isVisible": true,
  "layerListExpandedType": 0,
  "name": "Fill 944",
  "nameIsFixed": false,
  "pointRadiusBehaviour": 1,
  "points": [
    {
      "_class": "curvePoint",
      "cornerRadius": 0,
      "curveFrom": "{1, 0.5}",
      "curveMode": 1,
      "curveTo": "{1, 0.5}",
      "hasCurveFrom": false,
      "hasCurveTo": false,
      "point": "{1, 0.5}"
    },
    {
      "_class": "curvePoint",
      "cornerRadius": 0,
      "curveFrom": "{0.50002183215439711, 1}",
      "curveMode": 1,
      "curveTo": "{0.50002183215439711, 1}",
      "hasCurveFrom": false,
      "hasCurveTo": false,
      "point": "{0.50002183215439711, 1}"
    },
    {
      "_class": "curvePoint",
      "cornerRadius": 0,
      "curveFrom": "{0, 0.5}",
      "curveMode": 1,
      "curveTo": "{0, 0.5}",
      "hasCurveFrom": false,
      "hasCurveTo": false,
      "point": "{0, 0.5}"
    },
    {
      "_class": "curvePoint",
      "cornerRadius": 0,
      "curveFrom": "{0.50002183215439711, 0}",
      "curveMode": 1,
      "curveTo": "{0.50002183215439711, 0}",
      "hasCurveFrom": false,
      "hasCurveTo": false,
      "point": "{0.50002183215439711, 0}"
    }
  ],
  "resizingConstraint": 63,
  "resizingType": 0,
  "rotation": 0,
  "shouldBreakMaskChain": false,
  "style": {
    "_class": "style",
    "do_objectID": "3899C236-A4C6-4535-9889-7565ED7F7842",
    "endMarkerType": 0,
    "fills": [
      {
        "_class": "fill",
        "color": {
          "_class": "color",
          "alpha": 1,
          "blue": 0.961,
          "green": 0.004,
          "red": 1
        },
        "fillType": 0,
        "isEnabled": true,
        "noiseIndex": 0,
        "noiseIntensity": 0,
        "patternFillType": 1,
        "patternTileScale": 1
      }
    ],
    "miterLimit": 10,
    "startMarkerType": 0,
    "windingRule": 1
  }
}