{
  "_class": "shapePath",
  "booleanOperation": -1,
  "clippingMaskMode": 0,
  "do_objectID": "75A40579-AE7A-45BA-AFF6-993772F7C408",
  "edited": true,
  "exportOptions": {
    "_class": "exportOptions",
    "do_objectID": "0A4515A9-7A60-4084-A379-D0D0519A54B6",
    "exportFormats": [
    ],
    "includedLayerIds": [
    ],
    "layerOptions": 0,
    "shouldTrim": false
  },
  "frame": {
    "_class": "rect",
    "constrainProportions": false,
    "do_objectID": "2D7C5853-C97C-47DC-9605-CBA99848E887",
    "height": 8.110295346681122,
    "width": 8.11029534668119,
    "x": 11.44444013282411,
    "y": 11.62172945174624
  },
  "hasClippingMask": false,
  "isClosed": true,
  "isFixedToViewport": false,
  "isFlippedHorizontal": false,
  "isFlippedVertical": false,
  "isLocked": false,
  "isVisible": true,
  "layerListExpandedType": 0,
  "name": "Path",
  "nameIsFixed": false,
  "pointRadiusBehaviour": 1,
  "points": [
    {
      "_class": "curvePoint",
      "cornerRadius": 0,
      "curveFrom": "{0, 1}",
      "curveMode": 1,
      "curveTo": "{0, 1}",
      "hasCurveFrom": false,
      "hasCurveTo": false,
      "point": "{0, 1}"
    },
    {
      "_class": "curvePoint",
      "cornerRadius": 0,
      "curveFrom": "{0.294547224926972, 0.53062317429406047}",
      "curveMode": 4,
      "curveTo": "{0, 0.54313534566699118}",
      "hasCurveFrom": true,
      "hasCurveTo": false,
      "point": "{0, 0.54313534566699118}"
    },
    {
      "_class": "curvePoint",
      "cornerRadius": 0,
      "curveFrom": "{0.54313534566699118, 0}",
      "curveMode": 4,
      "curveTo": "{0.53062317429406081, 0.29459591041869498}",
      "hasCurveFrom": false,
      "hasCurveTo": true,
      "point": "{0.54313534566699118, 0}"
    },
    {
      "_class": "curvePoint",
      "cornerRadius": 0,
      "curveFrom": "{0.9870496592015584, 0.54600778967867558}",
      "curveMode": 4,
      "curveTo": "{1, 0}",
      "hasCurveFrom": true,
      "hasCurveTo": false,
      "point": "{1, 0}"
    },
    {
      "_class": "curvePoint",
      "cornerRadius": 0,
      "curveFrom": "{0, 1}",
      "curveMode": 4,
      "curveTo": "{0.54600778967867558, 0.98709834469328139}",
      "hasCurveFrom": false,
      "hasCurveTo": true,
      "point": "{0, 1}"
    }
  ],
  "resizingConstraint": 63,
  "resizingType": 0,
  "rotation": 0,
  "shouldBreakMaskChain": false,
  "style": {
    "_class": "style",
    "blur": {
      "_class": "blur",
      "center": "{0.5, 0.5}",
      "do_objectID": "C0388221-0874-4986-9ACE-1B6C16A587FA",
      "isEnabled": false,
      "motionAngle": 0,
      "radius": 12.4966814159292,
      "saturation": 1,
      "type": 0
    },
    "do_objectID": "667994AC-5651-4858-9B8B-ADC9E7552D17",
    "endMarkerType": 0,
    "miterLimit": 10,
    "startMarkerType": 0,
    "windingRule": 1
  }
}