{
  "_class": "group",
  "booleanOperation": -1,
  "clippingMaskMode": 0,
  "do_objectID": "E7200E0F-9DDC-4541-BA29-F4B05043AF34",
  "exportOptions": {
    "_class": "exportOptions",
    "do_objectID": "ED871512-F970-4548-95A9-3DBF91C9127F",
    "exportFormats": [
    ],
    "includedLayerIds": [
    ],
    "layerOptions": 0,
    "shouldTrim": false
  },
  "frame": {
    "_class": "rect",
    "constrainProportions": false,
    "do_objectID": "95FF1B26-B3DE-4EA9-890C-2F453FA947AF",
    "height": 22,
    "width": 22,
    "x": 51,
    "y": 5
  },
  "hasClickThrough": false,
  "hasClippingMask": false,
  "isFixedToViewport": false,
  "isFlippedHorizontal": false,
  "isFlippedVertical": false,
  "isLocked": false,
  "isVisible": true,
  "layerListExpandedType": 0,
  "layers": [
    {
      "class": "shapePath",
      "id": "C1EF688E-1731-41C4-829A-AC2DFD50EA50"
    },
    {
      "class": "shapeGroup",
      "id": "9E14F9E7-4FB7-496C-8137-CD0049BA524C"
    }
  ],
  "name": "Group 3",
  "nameIsFixed": false,
  "resizingConstraint": 63,
  "resizingType": 0,
  "rotation": 0,
  "shouldBreakMaskChain": false,
  "style": {
    "_class": "style",
    "blur": {
      "_class": "blur",
      "center": "{0.5, 0.5}",
      "do_objectID": "A4421443-6B34-4569-A678-A65B896313AF",
      "isEnabled": false,
      "motionAngle": 0,
      "radius": 12.4966814159292,
      "saturation": 1,
      "type": 0
    },
    "do_objectID": "736E919C-32AC-4FCD-837E-3CDDAEA37793",
    "endMarkerType": 0,
    "miterLimit": 10,
    "startMarkerType": 0,
    "windingRule": 1
  }
}