{
  "_class": "group",
  "booleanOperation": -1,
  "clippingMaskMode": 0,
  "do_objectID": "6609E26F-6247-4D39-95F8-CAE8E06254F0",
  "exportOptions": {
    "_class": "exportOptions",
    "exportFormats": [
    ],
    "includedLayerIds": [
    ],
    "layerOptions": 0,
    "shouldTrim": false
  },
  "frame": {
    "_class": "rect",
    "constrainProportions": false,
    "height": 121,
    "width": 19,
    "x": 0,
    "y": 0
  },
  "hasClickThrough": false,
  "hasClippingMask": false,
  "isFixedToViewport": false,
  "isFlippedHorizontal": false,
  "isFlippedVertical": false,
  "isLocked": false,
  "isVisible": true,
  "layerListExpandedType": 0,
  "layers": [
    {
      "class": "rectangle",
      "id": "F7B66FF6-C00C-42A5-B0B1-3E2D0B809D16"
    },
    {
      "class": "rectangle",
      "id": "4EA31809-7EA6-411D-AEC0-93BAE5E8802C"
    },
    {
      "class": "rectangle",
      "id": "62CF0767-406B-4616-9E18-AFE24881BA78"
    },
    {
      "class": "rectangle",
      "id": "4B8E67B9-FCEF-4CAA-BED3-FD61FF855A2E"
    }
  ],
  "name": "blocks",
  "nameIsFixed": true,
  "resizingConstraint": 63,
  "resizingType": 0,
  "rotation": 0,
  "shouldBreakMaskChain": false,
  "style": {
    "_class": "style",
    "endMarkerType": 0,
    "miterLimit": 10,
    "startMarkerType": 0,
    "windingRule": 1
  }
}