{
  "_class": "group",
  "booleanOperation": -1,
  "clippingMaskMode": 0,
  "do_objectID": "3B6F98CD-BF25-461F-9715-B3672902D024",
  "exportOptions": {
    "_class": "exportOptions",
    "do_objectID": "4C73A095-9AF5-4A56-8E02-76758839CF2A",
    "exportFormats": [
    ],
    "includedLayerIds": [
    ],
    "layerOptions": 0,
    "shouldTrim": false
  },
  "frame": {
    "_class": "rect",
    "constrainProportions": false,
    "do_objectID": "E27B4B0E-96AA-4994-A1EE-03E203757A18",
    "height": 8.691292875989445,
    "width": 8.691292875989445,
    "x": 20.27968337730871,
    "y": 1.448548812664908
  },
  "hasClickThrough": false,
  "hasClippingMask": false,
  "isFixedToViewport": false,
  "isFlippedHorizontal": false,
  "isFlippedVertical": false,
  "isLocked": false,
  "isVisible": true,
  "layerListExpandedType": 0,
  "layers": [
    {
      "class": "shapePath",
      "id": "22F066F2-DDE0-440C-A868-F09ED6474CA8"
    },
    {
      "class": "shapeGroup",
      "id": "81BA506E-C153-4330-9200-70E051E27C68"
    }
  ],
  "name": "Group 3",
  "nameIsFixed": false,
  "resizingConstraint": 63,
  "resizingType": 0,
  "rotation": 0,
  "shouldBreakMaskChain": false,
  "style": {
    "_class": "style",
    "blur": {
      "_class": "blur",
      "center": "{0.5, 0.5}",
      "do_objectID": "4D106AC9-7371-41F5-A10C-7D0C42EF1927",
      "isEnabled": false,
      "motionAngle": 0,
      "radius": 4.828496042216359,
      "saturation": 1,
      "type": 0
    },
    "do_objectID": "F54607DE-B27C-4FB6-9546-1CFB61733DD7",
    "endMarkerType": 0,
    "miterLimit": 10,
    "startMarkerType": 0,
    "windingRule": 1
  }
}