{
  "_class": "group",
  "booleanOperation": -1,
  "clippingMaskMode": 0,
  "do_objectID": "B12C8853-29DD-4DCE-834F-48B89CB17AFE",
  "exportOptions": {
    "_class": "exportOptions",
    "do_objectID": "9D947C2C-CF35-4A0E-9835-9F0F077F8F98",
    "exportFormats": [
    ],
    "includedLayerIds": [
    ],
    "layerOptions": 0,
    "shouldTrim": false
  },
  "frame": {
    "_class": "rect",
    "constrainProportions": false,
    "do_objectID": "70552DE9-36D0-4C7F-B436-7CD9C9145171",
    "height": 45,
    "width": 46,
    "x": 426.1187096774194,
    "y": 0
  },
  "hasClickThrough": false,
  "hasClippingMask": false,
  "isFixedToViewport": false,
  "isFlippedHorizontal": false,
  "isFlippedVertical": false,
  "isLocked": false,
  "isVisible": true,
  "layerListExpandedType": 0,
  "layers": [
    {
      "class": "shapePath",
      "id": "DDA480BD-74D6-4F31-B51A-C604B80DA4B5"
    },
    {
      "class": "shapePath",
      "id": "82D4D1F7-02F6-43B2-99F6-095BC07C045F"
    }
  ],
  "name": "Group 940",
  "nameIsFixed": false,
  "resizingConstraint": 63,
  "resizingType": 0,
  "rotation": 0,
  "shouldBreakMaskChain": false,
  "style": {
    "_class": "style",
    "do_objectID": "03BA1CBB-92B1-43CD-83FD-5492AA2BD72A",
    "endMarkerType": 0,
    "miterLimit": 10,
    "startMarkerType": 0,
    "windingRule": 1
  }
}