{
  "_class": "group",
  "booleanOperation": -1,
  "clippingMaskMode": 0,
  "do_objectID": "39BFB50C-5FB0-44DD-8DD6-28009A660707",
  "exportOptions": {
    "_class": "exportOptions",
    "do_objectID": "27987AEB-BDCF-41EA-923F-0F29A56DF408",
    "exportFormats": [
    ],
    "includedLayerIds": [
    ],
    "layerOptions": 0,
    "shouldTrim": false
  },
  "frame": {
    "_class": "rect",
    "constrainProportions": false,
    "do_objectID": "5AE89194-9996-42FC-A311-DFAFB0FF001F",
    "height": 19.08,
    "width": 19.08,
    "x": 44.52,
    "y": 3.18
  },
  "hasClickThrough": false,
  "hasClippingMask": false,
  "isFixedToViewport": false,
  "isFlippedHorizontal": false,
  "isFlippedVertical": false,
  "isLocked": false,
  "isVisible": true,
  "layerListExpandedType": 0,
  "layers": [
    {
      "class": "shapePath",
      "id": "A6EFCDEA-92D7-4C8F-B088-727571B81872"
    },
    {
      "class": "shapeGroup",
      "id": "198FFC0D-35A9-4DF0-B69B-F3D5647FA66C"
    }
  ],
  "name": "Group 3",
  "nameIsFixed": false,
  "resizingConstraint": 63,
  "resizingType": 0,
  "rotation": 0,
  "shouldBreakMaskChain": false,
  "style": {
    "_class": "style",
    "blur": {
      "_class": "blur",
      "center": "{0.5, 0.5}",
      "do_objectID": "EDD5C245-F6C0-4CF0-B478-7358776555BE",
      "isEnabled": false,
      "motionAngle": 0,
      "radius": 10.6,
      "saturation": 1,
      "type": 0
    },
    "do_objectID": "B2D67548-E7F8-4AB4-9FCD-E6529F433DF5",
    "endMarkerType": 0,
    "miterLimit": 10,
    "startMarkerType": 0,
    "windingRule": 1
  }
}