{
  "_class": "text",
  "attributedString": {
    "_class": "attributedString",
    "attributes": [
      {
        "_class": "stringAttribute",
        "attributes": {
          "MSAttributedStringColorAttribute": {
            "_class": "color",
            "alpha": 1,
            "blue": 0,
            "green": 0,
            "red": 0
          },
          "MSAttributedStringFontAttribute": {
            "_class": "fontDescriptor",
            "attributes": {
              "name": "FranklinGothic-Book",
              "size": 14
            }
          },
          "paragraphStyle": {
            "_class": "paragraphStyle",
            "alignment": 0,
            "paragraphSpacing": 10
          },
          "textStyleVerticalAlignmentKey": 0
        },
        "length": 126,
        "location": 0
      }
    ],
    "string": "B.A. University of Notre Dame\nM.A. Eastern Washington University\nM.F.A. University of Idaho\nAssociate Professor\nmbreen@ewu.edu"
  },
  "automaticallyDrawOnUnderlyingPath": false,
  "booleanOperation": -1,
  "clippingMaskMode": 0,
  "do_objectID": "514F872E-F53F-44D4-AA84-2B82A72BF336",
  "dontSynchroniseWithSymbol": false,
  "exportOptions": {
    "_class": "exportOptions",
    "do_objectID": "9F818A99-C3A4-4DAE-AD61-3B323AAC0546",
    "exportFormats": [
    ],
    "includedLayerIds": [
    ],
    "layerOptions": 0,
    "shouldTrim": false
  },
  "frame": {
    "_class": "rect",
    "constrainProportions": false,
    "do_objectID": "F9EE282D-B40B-4F0A-9239-86339FB63543",
    "height": 173,
    "width": 182,
    "x": 2,
    "y": 5510
  },
  "glyphBounds": "{{0, 3}, {173, 131}}",
  "hasClippingMask": false,
  "isFixedToViewport": false,
  "isFlippedHorizontal": false,
  "isFlippedVertical": false,
  "isLocked": false,
  "isVisible": true,
  "layerListExpandedType": 0,
  "lineSpacingBehaviour": 2,
  "name": "B.A. University of N",
  "nameIsFixed": false,
  "resizingConstraint": 63,
  "resizingType": 0,
  "rotation": 0,
  "sharedStyleID": "FD6A3FAA-2439-4FC0-A771-7FAC12599414",
  "shouldBreakMaskChain": false,
  "style": {
    "_class": "style",
    "do_objectID": "B7AA7978-B349-429E-B778-8DC58EE380CA",
    "endMarkerType": 0,
    "miterLimit": 10,
    "startMarkerType": 0,
    "textStyle": {
      "_class": "textStyle",
      "do_objectID": "01F11609-30E8-4D29-ABF6-D406E93C0854",
      "encodedAttributes": {
        "MSAttributedStringColorAttribute": {
          "_class": "color",
          "alpha": 1,
          "blue": 0,
          "green": 0,
          "red": 0
        },
        "MSAttributedStringFontAttribute": {
          "_class": "fontDescriptor",
          "attributes": {
            "name": "FranklinGothic-Book",
            "size": 14
          }
        },
        "paragraphStyle": {
          "_class": "paragraphStyle",
          "alignment": 0,
          "paragraphSpacing": 10
        },
        "textStyleVerticalAlignmentKey": 0
      },
      "verticalAlignment": 0
    },
    "windingRule": 1
  },
  "textBehaviour": 2
}