{
  "_class": "text",
  "attributedString": {
    "_class": "attributedString",
    "attributes": [
      {
        "_class": "stringAttribute",
        "attributes": {
          "MSAttributedStringColorAttribute": {
            "_class": "color",
            "alpha": 1,
            "blue": 0,
            "green": 0,
            "red": 0
          },
          "MSAttributedStringFontAttribute": {
            "_class": "fontDescriptor",
            "attributes": {
              "name": "Perpetua-Bold",
              "size": 60
            }
          },
          "paragraphStyle": {
            "_class": "paragraphStyle",
            "alignment": 2
          },
          "textStyleVerticalAlignmentKey": 0
        },
        "length": 22,
        "location": 0
      }
    ],
    "string": "Senior Design Showcase"
  },
  "automaticallyDrawOnUnderlyingPath": false,
  "booleanOperation": -1,
  "clippingMaskMode": 0,
  "do_objectID": "E258E45F-D179-41D5-82C3-5C1F8DE85FBA",
  "dontSynchroniseWithSymbol": false,
  "exportOptions": {
    "_class": "exportOptions",
    "do_objectID": "C505FC16-E6B0-48BA-A853-9B5D489163B0",
    "exportFormats": [
    ],
    "includedLayerIds": [
    ],
    "layerOptions": 0,
    "shouldTrim": false
  },
  "frame": {
    "_class": "rect",
    "constrainProportions": false,
    "do_objectID": "A5BA6BEA-4493-4D80-951E-EB3434EBA76E",
    "height": 108,
    "width": 795,
    "x": 115,
    "y": 4150
  },
  "glyphBounds": "{{95, 11}, {606, 57}}",
  "hasClippingMask": false,
  "isFixedToViewport": false,
  "isFlippedHorizontal": false,
  "isFlippedVertical": false,
  "isLocked": false,
  "isVisible": true,
  "layerListExpandedType": 0,
  "lineSpacingBehaviour": 2,
  "name": "Senior Design Showca",
  "nameIsFixed": false,
  "resizingConstraint": 63,
  "resizingType": 0,
  "rotation": 0,
  "shouldBreakMaskChain": false,
  "style": {
    "_class": "style",
    "do_objectID": "621A0E3A-BF1B-4005-B723-5B2D70919D74",
    "endMarkerType": 0,
    "miterLimit": 10,
    "startMarkerType": 0,
    "textStyle": {
      "_class": "textStyle",
      "do_objectID": "532E0D8D-2F87-4A2C-912D-AAC2C672599A",
      "encodedAttributes": {
        "MSAttributedStringColorAttribute": {
          "_class": "color",
          "alpha": 1,
          "blue": 0,
          "green": 0,
          "red": 0
        },
        "MSAttributedStringFontAttribute": {
          "_class": "fontDescriptor",
          "attributes": {
            "name": "Perpetua-Bold",
            "size": 60
          }
        },
        "paragraphStyle": {
          "_class": "paragraphStyle",
          "alignment": 2
        },
        "textStyleVerticalAlignmentKey": 0
      },
      "verticalAlignment": 0
    },
    "windingRule": 1
  },
  "textBehaviour": 2
}