{
  "_class": "text",
  "attributedString": {
    "_class": "attributedString",
    "attributes": [
      {
        "_class": "stringAttribute",
        "attributes": {
          "MSAttributedStringColorAttribute": {
            "_class": "color",
            "alpha": 1,
            "blue": 0,
            "green": 0,
            "red": 0
          },
          "MSAttributedStringFontAttribute": {
            "_class": "fontDescriptor",
            "attributes": {
              "name": "Perpetua-Bold",
              "size": 72
            }
          },
          "paragraphStyle": {
            "_class": "paragraphStyle",
            "alignment": 2
          }
        },
        "length": 27,
        "location": 0
      }
    ],
    "string": "2018 Senior Design Showcase"
  },
  "automaticallyDrawOnUnderlyingPath": false,
  "booleanOperation": -1,
  "clippingMaskMode": 0,
  "do_objectID": "D642ED48-3A7B-44BB-AAE5-94D15F885E6D",
  "dontSynchroniseWithSymbol": false,
  "exportOptions": {
    "_class": "exportOptions",
    "do_objectID": "D2C07925-C8CC-4361-B2EA-4A8549F9BFA3",
    "exportFormats": [
    ],
    "includedLayerIds": [
    ],
    "layerOptions": 0,
    "shouldTrim": false
  },
  "frame": {
    "_class": "rect",
    "constrainProportions": false,
    "do_objectID": "BC447EF6-4D7D-4899-86D5-611FFBB52D84",
    "height": 108,
    "width": 959,
    "x": 32,
    "y": 2005
  },
  "glyphBounds": "{{41, 13}, {877, 68}}",
  "hasClippingMask": false,
  "isFixedToViewport": false,
  "isFlippedHorizontal": false,
  "isFlippedVertical": false,
  "isLocked": false,
  "isVisible": true,
  "layerListExpandedType": 0,
  "lineSpacingBehaviour": 2,
  "name": "2018 Senior Design S",
  "nameIsFixed": false,
  "resizingConstraint": 63,
  "resizingType": 0,
  "rotation": 0,
  "sharedStyleID": "BA422B22-F9D4-41B9-A425-A73D2AEE9340",
  "shouldBreakMaskChain": false,
  "style": {
    "_class": "style",
    "do_objectID": "E5BC2D4E-789F-4BC1-978E-A8F938BB0B34",
    "endMarkerType": 0,
    "miterLimit": 10,
    "startMarkerType": 0,
    "textStyle": {
      "_class": "textStyle",
      "do_objectID": "B83EC732-10FA-46CD-B352-1622083B5A9C",
      "encodedAttributes": {
        "MSAttributedStringColorAttribute": {
          "_class": "color",
          "alpha": 1,
          "blue": 0,
          "green": 0,
          "red": 0
        },
        "MSAttributedStringFontAttribute": {
          "_class": "fontDescriptor",
          "attributes": {
            "name": "Perpetua-Bold",
            "size": 72
          }
        },
        "paragraphStyle": {
          "_class": "paragraphStyle",
          "alignment": 2
        }
      },
      "verticalAlignment": 1
    },
    "windingRule": 1
  },
  "textBehaviour": 2
}